Verilog/clock.v
module digital_clock_with_menu #(
    parameter CLK_PER_SEC = 50_000_000,
    parameter CLK100_PER_SEC = 500_000
) (
    input clk,
    input reset,
    input mode_24h,
    // Time set inputs
    input set_time,
    input [5:0] in_hour,
    input [5:0] in_minute,
    input [5:0] in_second,
    // Alarm set inputs
    input set_alarm,
    input [5:0] in_alarm_hr,
    input [5:0] in_alarm_min,
    // Timer inputs
    input start_timer,
    input pause_timer,
    input [3:0] in_timer_min,
    // Stopwatch inputs
    input sw_start,
    input sw_stop,
    input sw_reset,
    input [2:0] menu_select,
    // Mode 3 date set
    input [4:0] in_day,
    input [3:0] in_month,
    input [11:0] in_year,
    // Outputs
    output reg [5:0] hour,
    output reg [5:0] minute,
    output reg [5:0] second,
    output reg am_pm,
    output reg [4:0] day,
    output reg [3:0] month,
    output reg [11:0] year,
    output reg timer_buzzer,
    output reg alarm_buzzer,
    output reg [5:0] sw_min,
    output reg [5:0] sw_sec,
    output reg [6:0] sw_hun
);
    reg [5:0] alarm_hr_r, alarm_min_r;
    reg [11:0] timer_count;
    reg timer_running, timer_paused, stopwatch_running, tick_1hz, tick_100hz;
    reg [25:0] clk_div;
    reg [18:0] clk_div_100hz;
    reg [3:0] alarm_ring_timer = 0; 
    // 1 Hz & 100 Hz dividers
    // Asynchronous reset
    always @(posedge clk or posedge reset) begin
        if (reset) begin
            clk_div <= 0;
	    tick_1hz <= 0;
            clk_div_100hz <= 0; 
	    tick_100hz <= 0;
        end else begin
            clk_div <= (clk_div == CLK_PER_SEC-1) ? 0 : clk_div + 1;
            tick_1hz <= (clk_div == CLK_PER_SEC-1);
            clk_div_100hz <= (clk_div_100hz == CLK100_PER_SEC-1) ? 0 : clk_div_100hz + 1;
            tick_100hz <= (clk_div_100hz == CLK100_PER_SEC-1);
        end
    end
    // Leap-year condition
    function is_leap_year(input [11:0] y);
        is_leap_year = ((y%4==0)&&(y%100!=0))||(y%400==0) ;
    endfunction
    // Days-in-month
    function [5:0] days_in_month(input [3:0] m, input [11:0] y);
        case(m)
            4'd1,4'd3,4'd5,4'd7,4'd8,4'd10,4'd12: days_in_month = 31;
            4'd4,4'd6,4'd9,4'd11: days_in_month = 30;
            4'd2: days_in_month = is_leap_year(y) ? 29 : 28;
            default: days_in_month = 30;
        endcase
    endfunction
    // Main logic
    reg next_is_midnight;
    always @(posedge clk or posedge reset) begin
        if (reset) begin
            hour <= 12; 
	    minute <= 0; 
	    second <= 0; 
	    am_pm <= 0;
            day <= 1; 
	    month <= 1; 
	    year <= 2020;
            alarm_hr_r <= 0; 
	    alarm_min_r <= 0; 
	    alarm_buzzer <= 0;
            timer_count <= 0; 
	    timer_running <= 0; 
	    timer_paused <= 0; 
	    timer_buzzer <= 0;
            sw_min <= 0; 
	    sw_sec <= 0; 
	    sw_hun <= 0; 
	    stopwatch_running <= 0;
        end else begin
            next_is_midnight = 0;  // Initialize next_is_midnight to 0
            // Advance time on tick_1hz
            if (set_time && menu_select == 3'd0) begin
                hour   <= in_hour;
                minute <= in_minute;
                second <= in_second;
                am_pm  <= (!mode_24h && in_hour >= 12);
            end else if (tick_1hz) begin
                if (mode_24h) begin
                    next_is_midnight = (hour == 6'd23 && minute == 6'd59 && second == 6'd59);
                end else begin
                    next_is_midnight = (hour == 6'd11 && minute == 6'd59 && second == 6'd59 && am_pm == 1);
                end
                // Incrementing time
                if (second == 6'd59) begin
                    second <= 0;
                    if (minute == 6'd59) begin
                        minute <= 0;
			// AM/PM 
                        if (mode_24h) begin
                            if (hour == 6'd23) hour <= 0;
                            else hour <= hour + 1;
                        end else begin
                            if (hour == 6'd11) begin hour <= 12; am_pm <= ~am_pm; end
                            else if (hour == 6'd12) hour <= 1;
                            else hour <= hour + 1;
                        end
                    end else minute <= minute + 1;
                end else second <= second + 1;
                // Increasing date if midnight is crossed
                if (next_is_midnight) begin
                    if (day == days_in_month(month,year)) begin
                        day <= 1;
                        if (month == 12) begin month <= 1; year <= year + 1; end
                        else month <= month + 1;
                    end else day <= day + 1;
		// Resetting date as per question
                if ( year > 2025 || (year == 2025 && (month > 4 || (month == 4 && day >= 30))) ) begin
                        day <= 1; month <= 1; year <= 2020;
                    end
                end
            end
            case(menu_select)
                3'd1: begin // Timer
                    if (start_timer) begin
                        timer_count <= in_timer_min * 60;
                        timer_running <= 1;
                        timer_paused <= 0;
                        timer_buzzer <= 0;
                    end else if (pause_timer) timer_paused <= ~timer_paused;
                    if (tick_1hz && timer_running && !timer_paused) begin
                        if (timer_count > 0) timer_count <= timer_count - 1;
                        else begin timer_running <= 0; timer_buzzer <= 1; end
                    end
                end
                3'd2: begin // Alarm
    			if (set_alarm) begin
        			alarm_hr_r <= in_alarm_hr;
        			alarm_min_r <= in_alarm_min;
    			end
		end
                3'd3: begin // Date set
                    if (set_time) begin
                        day   <= in_day;
                        month <= in_month;
                        year  <= in_year;
                    end
                end
                3'd4: begin // Stopwatch
                    if (sw_reset) begin
                        sw_min <= 0;
			sw_sec <= 0; 
			sw_hun <= 0; 
			stopwatch_running <= 0;
                    end else if (sw_start) stopwatch_running <= 1;
                    else if (sw_stop) stopwatch_running <= 0;
                    if (tick_100hz && stopwatch_running) begin
                        if (sw_hun == 99) begin
                            sw_hun <= 0;
                            if (sw_sec == 59) begin
                                sw_sec <= 0;
                                if (sw_min == 59) sw_min <= 0;
                                else sw_min <= sw_min + 1;
                            end else sw_sec <= sw_sec + 1;
                        end else sw_hun <= sw_hun + 1;
                    end
                end
             endcase
// Ringing alarm for 10 seconds
if (tick_1hz) begin
    if (hour == alarm_hr_r && minute == alarm_min_r && second == 0)
        alarm_ring_timer <= 4'd10;
    else if (alarm_ring_timer > 0)
        alarm_ring_timer <= alarm_ring_timer - 1;

    alarm_buzzer <= (alarm_ring_timer > 0);
end
end
end
endmodule

Verilog/tb_clock.v
`timescale 1ns / 1ps

module tb_digital_clock_with_menu;
  // Inputs
  reg clk, reset;
  reg mode_24h, set_time, set_alarm, start_timer, pause_timer;
  reg [5:0] in_hour, in_minute, in_second;
  reg [5:0] in_alarm_hr, in_alarm_min;
  reg [3:0] in_timer_min;
  reg sw_start, sw_stop, sw_reset;
  reg [2:0] menu_select;
  reg [4:0] in_day;
  reg [3:0] in_month;
  reg [11:0] in_year;
  // Outputs
  wire [5:0] hour, minute, second;
  wire am_pm;
  wire [4:0] day;
  wire [3:0] month;
  wire [11:0] year;
  wire timer_buzzer, alarm_buzzer;
  wire [5:0] sw_min, sw_sec;
  wire [6:0] sw_hun;
  // Instantiate DUT with fast-sim dividers
  digital_clock_with_menu #(
    .CLK_PER_SEC(10),  // “1 Hz” every 10 clocks
    .CLK100_PER_SEC(2)   // “100 Hz” every 2 clocks
  ) uut (
    .clk(clk),
    .reset(reset),
    .mode_24h(mode_24h),
    .set_time(set_time),
    .in_hour(in_hour),
    .in_minute(in_minute),
    .in_second(in_second),
    .set_alarm(set_alarm),
    .in_alarm_hr(in_alarm_hr),
    .in_alarm_min(in_alarm_min),
    .start_timer(start_timer),
    .pause_timer(pause_timer),
    .in_timer_min(in_timer_min),
    .sw_start(sw_start),
    .sw_stop(sw_stop),
    .sw_reset(sw_reset),
    .menu_select(menu_select),
    .in_day(in_day),
    .in_month(in_month),
    .in_year(in_year),
    .hour(hour),
    .minute(minute),
    .second(second),
    .am_pm(am_pm),
    .day(day),
    .month(month),
    .year(year),
    .timer_buzzer(timer_buzzer),
    .alarm_buzzer(alarm_buzzer),
    .sw_min(sw_min),
    .sw_sec(sw_sec),
    .sw_hun(sw_hun)
  );
  // 100 MHz clock → 10 ns period
  initial clk = 0;
  always #5 clk = ~clk;
  initial begin
    $dumpfile("gtk.vcd");
    $dumpvars(0, tb_digital_clock_with_menu);
    // Resetting initially
    reset = 1;
    menu_select = 0;
    mode_24h = 1;
    set_time = 0;
    set_alarm = 0;
    start_timer = 0;
    pause_timer = 0;
    sw_start = 0;
    sw_stop = 0;
    sw_reset = 0;
    #20 reset = 0;
    // MODE 0: 24 h rollover
    $display("\n24-hour clock");
    menu_select = 3'd0;
    mode_24h = 1;
    in_hour = 6'd23;
    in_minute = 6'd59;
    in_second = 6'd50;
    set_time = 1; #10 set_time = 0;
    repeat (14) begin
      #100;
      $display("  %02d:%02d:%02d  %02d-%02d-%04d", hour, minute, second, day, month, year);
    end
    // MODE 0: 12 h AM/PM toggle
    $display("\n12-hour clock");
    reset = 1; #10 reset = 0;
    mode_24h = 0;
    in_hour = 6'd11;
    in_minute = 6'd59;
    in_second = 6'd55;
    set_time = 1; #10 set_time = 0;
    repeat (10) begin
      #100;
      $display("  %02d:%02d:%02d %s", hour, minute, second, am_pm ? "PM" : "AM");
    end
    // MODE 1: Timer (1 min) with pause/unpause
    $display("\n1-minute timer");
    reset = 1; #10 reset = 0;
    menu_select = 3'd1;
    in_timer_min = 4'd1;
    start_timer = 1; #10 start_timer  = 0;
    // first 3 ticks:
    $display("Starting countdown ... ");
    repeat (3) begin
      #100;
      $display("timer=%2d buzzer_state=%b", uut.timer_count, timer_buzzer);
    end
    // pause for one tick
    pause_timer = 1; #10 pause_timer = 0;
    #100;
    $display("Paused ... timer=%2d  buzzer_state=%b", uut.timer_count, timer_buzzer);
    // unpause and finish three more ticks
    pause_timer = 1; #10 pause_timer = 0;
    repeat (59) begin
      #100;
      $display("timer=%2d  buzzer_state=%b", uut.timer_count, timer_buzzer);
    end
    // MODE 2: Alarm (sample through 07:00:00)
    $display("\nAlarm set at 07:00:00");
    reset = 1; #10 reset = 0;
    menu_select = 3'd0;
    in_hour = 6'd6;
    in_minute = 6'd59;
    in_second = 6'd55;
    set_time = 1; #10 set_time = 0;
    menu_select = 3'd2;
    in_alarm_hr = 6'd7;
    in_alarm_min = 6'd0;
    set_alarm = 1; #10 set_alarm = 0;
    repeat (20) begin
      #100;
      $display("  %02d:%02d:%02d  alarm_buzzer=%b", hour, minute, second, alarm_buzzer);
    end
    // MODE 3: Date set & display
    $display("\nSetting date to 28-2-2024");
    $display("Before setting - \n Date = %0d:%0d:%0d", day, month, year);
    reset = 1; #10 reset = 0;
    menu_select = 3'd3;
    in_day = 5'd30;
    in_month = 4'd6;
    in_year = 12'd2024;
    set_time = 1; #10 set_time = 0;
    #100;
    $display("After setting - \nDate = %0d:%0d:%0d", day, month, year);
    // MODE 0: 24 h rollover
    $display("\nSetting time after setting date");
    menu_select = 3'd0;
    mode_24h = 1;
    in_hour = 6'd23;
    in_minute = 6'd59;
    in_second = 6'd50;	
    set_time = 1; #10 set_time = 0;
    repeat (14) begin
      #100;
      $display("  %02d:%02d:%02d  %02d-%02d-%04d", hour, minute, second, day, month, year);
    end
    $display("Resetting date to 1-1-20 after 30-4-25");
    reset = 1; #10 reset = 0;
    menu_select = 3'd3;
    in_day = 5'd30;
    in_month = 4'd4;
    in_year = 12'd2025;
    set_time = 1; #10 set_time = 0;
    #100;
    menu_select = 3'd0;
    mode_24h = 1;
    in_hour = 6'd23;
    in_minute = 6'd59;
    in_second = 6'd55;
    set_time = 1; #10 set_time = 0;
    repeat (10) begin
      #100;
      $display("  %02d:%02d:%02d  %02d-%02d-%04d", hour, minute, second, day, month, year);
    end
     $display("\n28-2 to 1-3 during non-leap years");
     reset = 1; #10 reset = 0;
    menu_select  = 3'd3;
    in_day = 5'd28;
    in_month = 4'd2;
    in_year = 12'd2023;
    set_time = 1; #10 set_time = 0;
    #100;
    menu_select = 3'd0;
    mode_24h = 1;
    in_hour = 6'd23;
    in_minute = 6'd59;
    in_second = 6'd55;
    set_time = 1; #10 set_time = 0;
    repeat (10) begin
      #100;
      $display("  %02d:%02d:%02d  %02d-%02d-%04d", hour, minute, second, day, month, year);
    end
    $display("\n28-2 to 29-2 during leap years");
     reset = 1; #10 reset = 0;
    menu_select = 3'd3;
    in_day = 5'd28;
    in_month = 4'd2;
    in_year = 12'd2020;
    set_time = 1; #10 set_time = 0;
    #100;
    menu_select = 3'd0;
    mode_24h = 1;
    in_hour = 6'd23;
    in_minute = 6'd59;
    in_second = 6'd55;
    set_time = 1; #10 set_time = 0;
    repeat (10) begin
      #100;
      $display("  %02d:%02d:%02d  %02d-%02d-%04d", hour, minute, second, day, month, year);
    end
    $display("\n29-2 to 1-3 during leap years");
     reset = 1; #10 reset = 0;
    menu_select = 3'd3;
    in_day = 5'd29;
    in_month = 4'd2;
    in_year = 12'd2020;
    set_time = 1; #10 set_time = 0;
    #100;
    menu_select = 3'd0;
    mode_24h = 1;
    in_hour = 6'd23;
    in_minute = 6'd59;
    in_second = 6'd55;
    set_time = 1; #10 set_time = 0;
    repeat (10) begin
      #100;
      $display("  %02d:%02d:%02d  %02d-%02d-%04d", hour, minute, second, day, month, year);
    end
    // MODE 4: Stopwatch 2.00 s
    $display("\nStopwatch for 2s");
    reset = 1; #10 reset = 0;
    menu_select = 3'd4;
    sw_reset = 1; #10 sw_reset = 0;
    sw_start = 1;
    repeat (200) #20;  // 200 ticks @20 ns = 2.00 µs sim → 2.00 s logical
    $display("%02d:%02d:%02d", sw_min, sw_sec, sw_hun);
    sw_start = 0;
    #100;
    #20 $finish;
  end

endmodule

Verilog/gtk.vcd
$date
	Thu May  8 09:43:53 2025
$end
$version
	Icarus Verilog
$end
$timescale
	1ps
$end
$scope module tb_digital_clock_with_menu $end
$var wire 12 ! year [11:0] $end
$var wire 1 " timer_buzzer $end
$var wire 6 # sw_sec [5:0] $end
$var wire 6 $ sw_min [5:0] $end
$var wire 7 % sw_hun [6:0] $end
$var wire 6 & second [5:0] $end
$var wire 4 ' month [3:0] $end
$var wire 6 ( minute [5:0] $end
$var wire 6 ) hour [5:0] $end
$var wire 5 * day [4:0] $end
$var wire 1 + am_pm $end
$var wire 1 , alarm_buzzer $end
$var reg 1 - clk $end
$var reg 6 . in_alarm_hr [5:0] $end
$var reg 6 / in_alarm_min [5:0] $end
$var reg 5 0 in_day [4:0] $end
$var reg 6 1 in_hour [5:0] $end
$var reg 6 2 in_minute [5:0] $end
$var reg 4 3 in_month [3:0] $end
$var reg 6 4 in_second [5:0] $end
$var reg 4 5 in_timer_min [3:0] $end
$var reg 12 6 in_year [11:0] $end
$var reg 3 7 menu_select [2:0] $end
$var reg 1 8 mode_24h $end
$var reg 1 9 pause_timer $end
$var reg 1 : reset $end
$var reg 1 ; set_alarm $end
$var reg 1 < set_time $end
$var reg 1 = start_timer $end
$var reg 1 > sw_reset $end
$var reg 1 ? sw_start $end
$var reg 1 @ sw_stop $end
$scope module uut $end
$var wire 1 - clk $end
$var wire 6 A in_alarm_hr [5:0] $end
$var wire 6 B in_alarm_min [5:0] $end
$var wire 5 C in_day [4:0] $end
$var wire 6 D in_hour [5:0] $end
$var wire 6 E in_minute [5:0] $end
$var wire 4 F in_month [3:0] $end
$var wire 6 G in_second [5:0] $end
$var wire 4 H in_timer_min [3:0] $end
$var wire 12 I in_year [11:0] $end
$var wire 3 J menu_select [2:0] $end
$var wire 1 8 mode_24h $end
$var wire 1 9 pause_timer $end
$var wire 1 : reset $end
$var wire 1 ; set_alarm $end
$var wire 1 < set_time $end
$var wire 1 = start_timer $end
$var wire 1 > sw_reset $end
$var wire 1 ? sw_start $end
$var wire 1 @ sw_stop $end
$var parameter 32 K CLK100_PER_SEC $end
$var parameter 32 L CLK_PER_SEC $end
$var reg 1 , alarm_buzzer $end
$var reg 6 M alarm_hr_r [5:0] $end
$var reg 6 N alarm_min_r [5:0] $end
$var reg 4 O alarm_ring_timer [3:0] $end
$var reg 1 + am_pm $end
$var reg 26 P clk_div [25:0] $end
$var reg 19 Q clk_div_100hz [18:0] $end
$var reg 5 R day [4:0] $end
$var reg 6 S hour [5:0] $end
$var reg 6 T minute [5:0] $end
$var reg 4 U month [3:0] $end
$var reg 1 V next_is_midnight $end
$var reg 6 W second [5:0] $end
$var reg 1 X stopwatch_running $end
$var reg 7 Y sw_hun [6:0] $end
$var reg 6 Z sw_min [5:0] $end
$var reg 6 [ sw_sec [5:0] $end
$var reg 1 \ tick_100hz $end
$var reg 1 ] tick_1hz $end
$var reg 1 " timer_buzzer $end
$var reg 12 ^ timer_count [11:0] $end
$var reg 1 _ timer_paused $end
$var reg 1 ` timer_running $end
$var reg 12 a year [11:0] $end
$scope function days_in_month $end
$var reg 4 b m [3:0] $end
$var reg 12 c y [11:0] $end
$upscope $end
$scope function is_leap_year $end
$var reg 12 d y [11:0] $end
$upscope $end
$upscope $end
$upscope $end
$enddefinitions $end
$comment Show the parameter values. $end
$dumpall
b1010 L
b10 K
$end
#0
$dumpvars
bx d
bx c
bx b
b11111100100 a
0`
0_
b0 ^
0]
0\
b0 [
b0 Z
b0 Y
0X
b0 W
xV
b1 U
b0 T
b1100 S
b1 R
b0 Q
b0 P
b0 O
b0 N
b0 M
b0 J
bx I
bx H
bx G
bx F
bx E
bx D
bx C
bx B
bx A
0@
0?
0>
0=
0<
0;
1:
09
18
b0 7
bx 6
bx 5
bx 4
bx 3
bx 2
bx 1
bx 0
bx /
bx .
0-
0,
0+
b1 *
b1100 )
b0 (
b1 '
b0 &
b0 %
b0 $
b0 #
0"
b11111100100 !
$end
#5000
1-
#10000
0-
#15000
1-
#20000
0-
1<
b110010 4
b110010 G
b111011 2
b111011 E
b10111 1
b10111 D
0:
#25000
b110010 &
b110010 W
b111011 (
b111011 T
b10111 )
b10111 S
b1 Q
b1 P
0V
1-
#30000
0-
0<
#35000
1\
b0 Q
b10 P
1-
#40000
0-
#45000
0\
b1 Q
b11 P
1-
#50000
0-
#55000
1\
b0 Q
b100 P
1-
#60000
0-
#65000
0\
b1 Q
b101 P
1-
#70000
0-
#75000
1\
b0 Q
b110 P
1-
#80000
0-
#85000
0\
b1 Q
b111 P
1-
#90000
0-
#95000
1\
b0 Q
b1000 P
1-
#100000
0-
#105000
0\
b1 Q
b1001 P
1-
#110000
0-
#115000
1\
b0 Q
1]
b0 P
1-
#120000
0-
#125000
b110011 &
b110011 W
0\
b1 Q
0]
b1 P
1-
#130000
0-
#135000
1\
b0 Q
b10 P
1-
#140000
0-
#145000
0\
b1 Q
b11 P
1-
#150000
0-
#155000
1\
b0 Q
b100 P
1-
#160000
0-
#165000
0\
b1 Q
b101 P
1-
#170000
0-
#175000
1\
b0 Q
b110 P
1-
#180000
0-
#185000
0\
b1 Q
b111 P
1-
#190000
0-
#195000
1\
b0 Q
b1000 P
1-
#200000
0-
#205000
0\
b1 Q
b1001 P
1-
#210000
0-
#215000
1\
b0 Q
1]
b0 P
1-
#220000
0-
#225000
b110100 &
b110100 W
0\
b1 Q
0]
b1 P
1-
#230000
0-
#235000
1\
b0 Q
b10 P
1-
#240000
0-
#245000
0\
b1 Q
b11 P
1-
#250000
0-
#255000
1\
b0 Q
b100 P
1-
#260000
0-
#265000
0\
b1 Q
b101 P
1-
#270000
0-
#275000
1\
b0 Q
b110 P
1-
#280000
0-
#285000
0\
b1 Q
b111 P
1-
#290000
0-
#295000
1\
b0 Q
b1000 P
1-
#300000
0-
#305000
0\
b1 Q
b1001 P
1-
#310000
0-
#315000
1\
b0 Q
1]
b0 P
1-
#320000
0-
#325000
b110101 &
b110101 W
0\
b1 Q
0]
b1 P
1-
#330000
0-
#335000
1\
b0 Q
b10 P
1-
#340000
0-
#345000
0\
b1 Q
b11 P
1-
#350000
0-
#355000
1\
b0 Q
b100 P
1-
#360000
0-
#365000
0\
b1 Q
b101 P
1-
#370000
0-
#375000
1\
b0 Q
b110 P
1-
#380000
0-
#385000
0\
b1 Q
b111 P
1-
#390000
0-
#395000
1\
b0 Q
b1000 P
1-
#400000
0-
#405000
0\
b1 Q
b1001 P
1-
#410000
0-
#415000
1\
b0 Q
1]
b0 P
1-
#420000
0-
#425000
b110110 &
b110110 W
0\
b1 Q
0]
b1 P
1-
#430000
0-
#435000
1\
b0 Q
b10 P
1-
#440000
0-
#445000
0\
b1 Q
b11 P
1-
#450000
0-
#455000
1\
b0 Q
b100 P
1-
#460000
0-
#465000
0\
b1 Q
b101 P
1-
#470000
0-
#475000
1\
b0 Q
b110 P
1-
#480000
0-
#485000
0\
b1 Q
b111 P
1-
#490000
0-
#495000
1\
b0 Q
b1000 P
1-
#500000
0-
#505000
0\
b1 Q
b1001 P
1-
#510000
0-
#515000
1\
b0 Q
1]
b0 P
1-
#520000
0-
#525000
b110111 &
b110111 W
0\
b1 Q
0]
b1 P
1-
#530000
0-
#535000
1\
b0 Q
b10 P
1-
#540000
0-
#545000
0\
b1 Q
b11 P
1-
#550000
0-
#555000
1\
b0 Q
b100 P
1-
#560000
0-
#565000
0\
b1 Q
b101 P
1-
#570000
0-
#575000
1\
b0 Q
b110 P
1-
#580000
0-
#585000
0\
b1 Q
b111 P
1-
#590000
0-
#595000
1\
b0 Q
b1000 P
1-
#600000
0-
#605000
0\
b1 Q
b1001 P
1-
#610000
0-
#615000
1\
b0 Q
1]
b0 P
1-
#620000
0-
#625000
b111000 &
b111000 W
0\
b1 Q
0]
b1 P
1-
#630000
0-
#635000
1\
b0 Q
b10 P
1-
#640000
0-
#645000
0\
b1 Q
b11 P
1-
#650000
0-
#655000
1\
b0 Q
b100 P
1-
#660000
0-
#665000
0\
b1 Q
b101 P
1-
#670000
0-
#675000
1\
b0 Q
b110 P
1-
#680000
0-
#685000
0\
b1 Q
b111 P
1-
#690000
0-
#695000
1\
b0 Q
b1000 P
1-
#700000
0-
#705000
0\
b1 Q
b1001 P
1-
#710000
0-
#715000
1\
b0 Q
1]
b0 P
1-
#720000
0-
#725000
b111001 &
b111001 W
0\
b1 Q
0]
b1 P
1-
#730000
0-
#735000
1\
b0 Q
b10 P
1-
#740000
0-
#745000
0\
b1 Q
b11 P
1-
#750000
0-
#755000
1\
b0 Q
b100 P
1-
#760000
0-
#765000
0\
b1 Q
b101 P
1-
#770000
0-
#775000
1\
b0 Q
b110 P
1-
#780000
0-
#785000
0\
b1 Q
b111 P
1-
#790000
0-
#795000
1\
b0 Q
b1000 P
1-
#800000
0-
#805000
0\
b1 Q
b1001 P
1-
#810000
0-
#815000
1\
b0 Q
1]
b0 P
1-
#820000
0-
#825000
b111010 &
b111010 W
0\
b1 Q
0]
b1 P
1-
#830000
0-
#835000
1\
b0 Q
b10 P
1-
#840000
0-
#845000
0\
b1 Q
b11 P
1-
#850000
0-
#855000
1\
b0 Q
b100 P
1-
#860000
0-
#865000
0\
b1 Q
b101 P
1-
#870000
0-
#875000
1\
b0 Q
b110 P
1-
#880000
0-
#885000
0\
b1 Q
b111 P
1-
#890000
0-
#895000
1\
b0 Q
b1000 P
1-
#900000
0-
#905000
0\
b1 Q
b1001 P
1-
#910000
0-
#915000
1\
b0 Q
1]
b0 P
1-
#920000
0-
#925000
b111011 &
b111011 W
0\
b1 Q
0]
b1 P
1-
#930000
0-
#935000
1\
b0 Q
b10 P
1-
#940000
0-
#945000
0\
b1 Q
b11 P
1-
#950000
0-
#955000
1\
b0 Q
b100 P
1-
#960000
0-
#965000
0\
b1 Q
b101 P
1-
#970000
0-
#975000
1\
b0 Q
b110 P
1-
#980000
0-
#985000
0\
b1 Q
b111 P
1-
#990000
0-
#995000
1\
b0 Q
b1000 P
1-
#1000000
0-
#1005000
0\
b1 Q
b1001 P
1-
#1010000
0-
#1015000
1\
b0 Q
1]
b0 P
1-
#1020000
0-
#1025000
b10 *
b10 R
b0 )
b0 S
b0 (
b0 T
b0 &
b0 W
0\
b1 Q
0]
b1 P
b1 b
b11111100100 c
1V
1-
#1030000
0-
#1035000
1\
b0 Q
b10 P
0V
1-
#1040000
0-
#1045000
0\
b1 Q
b11 P
1-
#1050000
0-
#1055000
1\
b0 Q
b100 P
1-
#1060000
0-
#1065000
0\
b1 Q
b101 P
1-
#1070000
0-
#1075000
1\
b0 Q
b110 P
1-
#1080000
0-
#1085000
0\
b1 Q
b111 P
1-
#1090000
0-
#1095000
1\
b0 Q
b1000 P
1-
#1100000
0-
#1105000
0\
b1 Q
b1001 P
1-
#1110000
0-
#1115000
1\
b0 Q
1]
b0 P
1-
#1120000
0-
#1125000
b1010 O
b1 &
b1 W
0\
b1 Q
0]
b1 P
1-
#1130000
0-
#1135000
1\
b0 Q
b10 P
1-
#1140000
0-
#1145000
0\
b1 Q
b11 P
1-
#1150000
0-
#1155000
1\
b0 Q
b100 P
1-
#1160000
0-
#1165000
0\
b1 Q
b101 P
1-
#1170000
0-
#1175000
1\
b0 Q
b110 P
1-
#1180000
0-
#1185000
0\
b1 Q
b111 P
1-
#1190000
0-
#1195000
1\
b0 Q
b1000 P
1-
#1200000
0-
#1205000
0\
b1 Q
b1001 P
1-
#1210000
0-
#1215000
1\
b0 Q
1]
b0 P
1-
#1220000
0-
#1225000
1,
b1001 O
b10 &
b10 W
0\
b1 Q
0]
b1 P
1-
#1230000
0-
#1235000
1\
b0 Q
b10 P
1-
#1240000
0-
#1245000
0\
b1 Q
b11 P
1-
#1250000
0-
#1255000
1\
b0 Q
b100 P
1-
#1260000
0-
#1265000
0\
b1 Q
b101 P
1-
#1270000
0-
#1275000
1\
b0 Q
b110 P
1-
#1280000
0-
#1285000
0\
b1 Q
b111 P
1-
#1290000
0-
#1295000
1\
b0 Q
b1000 P
1-
#1300000
0-
#1305000
0\
b1 Q
b1001 P
1-
#1310000
0-
#1315000
1\
b0 Q
1]
b0 P
1-
#1320000
0-
#1325000
b1000 O
b11 &
b11 W
0\
b1 Q
0]
b1 P
1-
#1330000
0-
#1335000
1\
b0 Q
b10 P
1-
#1340000
0-
#1345000
0\
b1 Q
b11 P
1-
#1350000
0-
#1355000
1\
b0 Q
b100 P
1-
#1360000
0-
#1365000
0\
b1 Q
b101 P
1-
#1370000
0-
#1375000
1\
b0 Q
b110 P
1-
#1380000
0-
#1385000
0\
b1 Q
b111 P
1-
#1390000
0-
#1395000
1\
b0 Q
b1000 P
1-
#1400000
0-
#1405000
0\
b1 Q
b1001 P
1-
#1410000
0-
#1415000
1\
b0 Q
1]
b0 P
1-
#1420000
0-
#1425000
b111 O
b100 &
b100 W
0\
b1 Q
0]
b1 P
1-
#1430000
b0 Q
b0 P
0,
b1 *
b1 R
b0 &
b0 W
b1100 )
b1100 S
0-
1:
#1435000
1-
#1440000
0-
1<
b110111 4
b110111 G
b1011 1
b1011 D
08
0:
#1445000
b1 Q
b1 P
b110111 &
b110111 W
b111011 (
b111011 T
b1011 )
b1011 S
1-
#1450000
0-
0<
#1455000
1\
b0 Q
b10 P
1-
#1460000
0-
#1465000
0\
b1 Q
b11 P
1-
#1470000
0-
#1475000
1\
b0 Q
b100 P
1-
#1480000
0-
#1485000
0\
b1 Q
b101 P
1-
#1490000
0-
#1495000
1\
b0 Q
b110 P
1-
#1500000
0-
#1505000
0\
b1 Q
b111 P
1-
#1510000
0-
#1515000
1\
b0 Q
b1000 P
1-
#1520000
0-
#1525000
0\
b1 Q
b1001 P
1-
#1530000
0-
#1535000
1\
b0 Q
1]
b0 P
1-
#1540000
0-
#1545000
0\
b1 Q
0]
b1 P
1,
b110 O
b111000 &
b111000 W
1-
#1550000
0-
#1555000
1\
b0 Q
b10 P
1-
#1560000
0-
#1565000
0\
b1 Q
b11 P
1-
#1570000
0-
#1575000
1\
b0 Q
b100 P
1-
#1580000
0-
#1585000
0\
b1 Q
b101 P
1-
#1590000
0-
#1595000
1\
b0 Q
b110 P
1-
#1600000
0-
#1605000
0\
b1 Q
b111 P
1-
#1610000
0-
#1615000
1\
b0 Q
b1000 P
1-
#1620000
0-
#1625000
0\
b1 Q
b1001 P
1-
#1630000
0-
#1635000
1\
b0 Q
1]
b0 P
1-
#1640000
0-
#1645000
0\
b1 Q
0]
b1 P
b101 O
b111001 &
b111001 W
1-
#1650000
0-
#1655000
1\
b0 Q
b10 P
1-
#1660000
0-
#1665000
0\
b1 Q
b11 P
1-
#1670000
0-
#1675000
1\
b0 Q
b100 P
1-
#1680000
0-
#1685000
0\
b1 Q
b101 P
1-
#1690000
0-
#1695000
1\
b0 Q
b110 P
1-
#1700000
0-
#1705000
0\
b1 Q
b111 P
1-
#1710000
0-
#1715000
1\
b0 Q
b1000 P
1-
#1720000
0-
#1725000
0\
b1 Q
b1001 P
1-
#1730000
0-
#1735000
1\
b0 Q
1]
b0 P
1-
#1740000
0-
#1745000
0\
b1 Q
0]
b1 P
b100 O
b111010 &
b111010 W
1-
#1750000
0-
#1755000
1\
b0 Q
b10 P
1-
#1760000
0-
#1765000
0\
b1 Q
b11 P
1-
#1770000
0-
#1775000
1\
b0 Q
b100 P
1-
#1780000
0-
#1785000
0\
b1 Q
b101 P
1-
#1790000
0-
#1795000
1\
b0 Q
b110 P
1-
#1800000
0-
#1805000
0\
b1 Q
b111 P
1-
#1810000
0-
#1815000
1\
b0 Q
b1000 P
1-
#1820000
0-
#1825000
0\
b1 Q
b1001 P
1-
#1830000
0-
#1835000
1\
b0 Q
1]
b0 P
1-
#1840000
0-
#1845000
0\
b1 Q
0]
b1 P
b11 O
b111011 &
b111011 W
1-
#1850000
0-
#1855000
1\
b0 Q
b10 P
1-
#1860000
0-
#1865000
0\
b1 Q
b11 P
1-
#1870000
0-
#1875000
1\
b0 Q
b100 P
1-
#1880000
0-
#1885000
0\
b1 Q
b101 P
1-
#1890000
0-
#1895000
1\
b0 Q
b110 P
1-
#1900000
0-
#1905000
0\
b1 Q
b111 P
1-
#1910000
0-
#1915000
1\
b0 Q
b1000 P
1-
#1920000
0-
#1925000
0\
b1 Q
b1001 P
1-
#1930000
0-
#1935000
1\
b0 Q
1]
b0 P
1-
#1940000
0-
#1945000
0\
b1 Q
0]
b1 P
b10 O
1+
b1100 )
b1100 S
b0 (
b0 T
b0 &
b0 W
1-
#1950000
0-
#1955000
1\
b0 Q
b10 P
1-
#1960000
0-
#1965000
0\
b1 Q
b11 P
1-
#1970000
0-
#1975000
1\
b0 Q
b100 P
1-
#1980000
0-
